<?xml version="1.0" encoding="UTF-8"?>
<objects serializationModel="Studio.02.03.00">
	<object class="AudioFile" id="{17565d0c-de61-40ef-80eb-689c14f2bc75}">
		<property name="assetPath">
			<value>SFX/Glass/sfx_-40.wav</value>
		</property>
		<property name="frequencyInKHz">
			<value>48</value>
		</property>
		<property name="channelCount">
			<value>1</value>
		</property>
		<property name="length">
			<value>0.83960416666666671</value>
		</property>
		<relationship name="masterAssetFolder">
			<destination>{039ffa74-b1d0-47e2-a685-4380e3f83039}</destination>
		</relationship>
	</object>
</objects>
